{
  "name": "Linear Theme - Dark Variant (No italics)",
  "type": "dark",
  "colors": {
    "terminal.ansiGreen": "#4CB782",
    "terminal.ansiBrightGreen": "#97D484",
    "terminal.ansiMagenta": "#cba0ff",
    "terminal.ansiYellow": "#ffcc6d",
    "terminal.ansiCyan": "#26B5CE",
    "terminal.ansiRed": "#eb5757",
    "foreground": "#c1c3c8",
    "icon.foreground": "#c1c3c8",
    "focusBorder": "#5e6ad2",
    "contrastBorder": "#3c3e44",
    "errorForeground": "#eb5757",
    "selection.background": "#5e6ad2",
    "button.background": "#5e6ad2",
    "button.hoverBackground": "#727ee6",
    "progressBar.background": "#727ee6",
    "input.background": "#46484e",
    "input.border": "#3c3e44",
    "inputOption.activeBackground": "#5e6ad2",
    "inputValidation.errorBorder": "#eb5757",
    "editor.background": "#1f2023",
    "editor.foreground": "#c1c3c8",
    "peekViewEditor.background": "#292a2e",
    "dropdown.background": "#292a2e",
    "dropdown.border": "#3c3e44",
    "sideBar.background": "#1f2023",
    "sideBar.border": "#2e2f33",
    "sideBarSectionHeader.background": "#323439",
    "activityBar.background": "#1f2023",
    "activityBar.foreground": "#c1c3c8",
    "activityBar.border": "#2e2f33",
    "activityBar.activeBorder": "#5e6ad2",
    "activityBarBadge.background": "#5e6ad2",
    "titleBar.activeBackground": "#292a2e",
    "titleBar.inactiveBackground": "#292a2e",
    "editor.selectionBackground": "#5163f961",
    "editor.selectionHighlightBackground": "#4456ec3b",
    "editor.wordHighlightBackground": "#ffffff00",
    "editor.wordHighlightBorder": "#5163f9ff",
    "editor.wordHighlightStrongBackground": "#ffffff00",
    "editor.wordHighlightStrongBorder": "#5163f9ff",
    "editor.hoverHighlightBackground": "#46484e",
    "editor.lineHighlightBackground": "#292a2e",
    "editor.lineHighlightBorder": "#292a2e",
    "editorWhitespace.foreground": "#46484e",
    "editorRuler.foreground": "#46484e",
    "editorIndentGuide.background": "#3c3e44",
    "editorIndentGuide.activeBackground": "#595c64",
    "tree.indentGuidesStroke": "#4f5259",
    "tree.tableColumnsBorder": "#4f5259",
    "editorCursor.foreground": "#c9d5ff",
    "terminalCursor.foreground": "#c9d5ff",
    "editorLineNumber.foreground": "#4f5259",
    "editorLineNumber.activeForeground": "#c1c3c8",
    "editorWidget.background": "#292a2e",
    "editorSuggestWidget.highlightForeground": "#8793fb",
    "editorSuggestWidget.selectedBackground": "#323439",
    "tab.activeBorderTop": "#5e6ad2",
    "tab.activeBackground": "#2e2f33",
    "tab.inactiveBackground": "#1f2023",
    "tab.border": "#2e2f33",
    "editorGroupHeader.tabsBackground": "#1f2023",
    "editorGroupHeader.border": "#292a2e",
    "editorGroupHeader.tabsBorder": "#2e2f33",
    "list.activeSelectionBackground": "#323439",
    "list.activeSelectionForeground": "#9ba7ff",
    "list.inactiveSelectionBackground": "#2e2f33",
    "list.inactiveSelectionForeground": "#9ba7ff",
    "list.hoverBackground": "#323439",
    "list.focusBackground": "#323439",
    "gitDecoration.modifiedResourceForeground": "#26B5CE",
    "gitDecoration.deletedResourceForeground": "#eb5757",
    "gitDecoration.untrackedResourceForeground": "#4CB782",
    "gitDecoration.ignoredResourceForeground": "#595c64",
    "gitDecoration.conflictingResourceForeground": "#F2994A",
    "panel.border": "#2e2f33",
    "panelTitle.activeBorder": "#5e6ad2",
    "badge.background": "#5e6ad2",
    "statusBar.background": "#292a2e"
  },
  "tokenColors": [
    {
      "name": "Comment",
      "scope": [
        "comment",
        "comment.block",
        "comment.line",
        "punctuation.definition.comment"
      ],
      "settings": {
        "fontStyle": "normal",
        "foreground": "#8b8e98"
      }
    },
    {
      "name": "Variables",
      "scope": [
        "variable",
        "variable.other",
        "variable.parameter",
        "entity.name.variable",
        "string constant.other.placeholder",
        "source.vue meta.object.member.ts meta.object.member.ts"
      ],
      "settings": {
        "foreground": "#e1e2e5"
      }
    },
    {
      "name": "Parameters",
      "scope": [
        "variable.parameter"
      ],
      "settings": {
        "foreground": "#e1e2e5"
      }
    },
    {
      "name": "Properties",
      "scope": [
        "constant.other.class",
        "variable.other.property",
        "variable.other.object.property"
      ],
      "settings": {
        "foreground": "#f3b7e9"
      }
    },
    {
      "name": "Invalid",
      "scope": [
        "invalid",
        "invalid.illegal"
      ],
      "settings": {
        "foreground": "#eb5757"
      }
    },
    {
      "name": "Keyword, Storage",
      "scope": [
        "keyword",
        "storage.type",
        "storage.modifier",
        "meta storage.type"
      ],
      "settings": {
        "fontStyle": "normal",
        "foreground": "#7e89ec"
      }
    },
    {
      "name": "Keyword, Operator",
      "scope": [
        "keyword.definition"
      ],
      "settings": {
        "foreground": "#8e82f8"
      }
    },
    {
      "name": "Comparison",
      "scope": [
        "keyword.operator.comparison",
        "keyword.operator.logical"
      ],
      "settings": {
        "foreground": "#a89fff"
      }
    },
    {
      "name": "Keyword, Storage",
      "scope": [
        "keyword.operator.logical.soil"
      ],
      "settings": {
        "foreground": "unset"
      }
    },
    {
      "name": "Operator, Misc",
      "scope": [
        "constant.other.color",
        "punctuation",
        "keyword.other.template",
        "keyword.other.substitution",
        "meta.brace",
        "punctuation.support.type.property-name",
        "expression.embbeded punctuation.definition.tag.begin.html",
        "expression.embbeded punctuation.definition.tag.end.html"
      ],
      "settings": {
        "fontStyle": "",
        "foreground": "#5da6b8"
      }
    },
    {
      "name": "Operator",
      "scope": [
        "keyword.operator"
      ],
      "settings": {
        "fontStyle": "",
        "foreground": "#5da6b8"
      }
    },
    {
      "name": "Operator, Misc",
      "scope": [
        "punctuation.definition.binding-pattern.object.js"
      ],
      "settings": {
        "foreground": "#5da6b8"
      }
    },
    {
      "name": "Tag Wrappers",
      "scope": [
        "punctuation.definition.tag.html",
        "punctuation.definition.tag.begin.html",
        "punctuation.definition.tag.end.html"
      ],
      "settings": {
        "foreground": "#74829e"
      }
    },
    {
      "name": "HTML Text",
      "scope": [
        "text.html",
        "meta.jsx.children.js"
      ],
      "settings": {
        "foreground": "#bdc4cc"
      }
    },
    {
      "name": "Operator, Misc",
      "scope": [
        "keyword.control",
        "entity.name.type.namespace",
        "keyword.other"
      ],
      "settings": {
        "fontStyle": "normal",
        "foreground": "#beb7ff"
      }
    },
    {
      "name": "Operator, Misc",
      "scope": [
        "keyword.control.flow",
        "keyword.control.export",
        "keyword.control.return",
        "meta.function.closure",
        "keyword.control.import",
        "keyword.control.from",
        "keyword.control.as",
        "keyword.other.namespace"
      ],
      "settings": {
        "fontStyle": "normal"
      }
    },
    {
      "name": "Tag",
      "scope": [
        "entity.name.tag",
        "meta.tag.sgml",
        "markup.deleted.git_gutter"
      ],
      "settings": {
        "foreground": "#83acf8"
      }
    },
    {
      "name": "Function and Method Call",
      "scope": [
        "meta.method.declaration meta.function-call entity.name.function",
        "meta.method-call entity.name.function",
        "meta.function-call entity.name.function",
        "variable.function",
        "support.function",
        "entity.name.function",
        "keyword.other.special-method"
      ],
      "settings": {
        "foreground": "#1abdda"
      }
    },
    {
      "name": "Function and Method Definition",
      "scope": [
        "meta.function entity.name.function",
        "meta.method entity.name.method",
        "meta.method.declaration entity.name.function",
        "meta.definition.method entity.name.function"
      ],
      "settings": {
        "foreground": "#61e6fd"
      }
    },
    {
      "name": "Other Variable, String Link",
      "scope": [
        "support.other.variable",
        "string.other.link"
      ],
      "settings": {
        "foreground": "#88e6d6"
      }
    },
    {
      "name": "Number, Constant, Tag Attribute, Embedded",
      "scope": [
        "constant.numeric",
        "constant.language",
        "support.constant",
        "constant.character",
        "constant.escape",
        "support.constant.property-value"
      ],
      "settings": {
        "foreground": "#97D484"
      }
    },
    {
      "name": "String, Symbols, Markup Heading",
      "scope": [
        "string",
        "constant.other.symbol",
        "constant.other.key",
        "markup.heading",
        "markup.inserted.git_gutter",
        "meta.group.braces.curly constant.other.object.key.js string.unquoted.label.js"
      ],
      "settings": {
        "foreground": "#ffd18b"
      }
    },
    {
      "name": "String Quotes",
      "scope": [
        "string punctuation.definition.string"
      ],
      "settings": {
        "foreground": "#ffcb8b9d"
      }
    },
    {
      "name": "Class, Support",
      "scope": [
        "entity.name",
        "entity.name.type.class",
        "support.type",
        "support.class",
        "new.expr meta.function-call entity.name.function",
        "markup.changed.git_gutter",
        "support.type.sys-types",
        "support.constant",
        "entity.name.type.namespace",
        "meta.tag.custom entity.name.tag.html",
        "source.vue invalid.illegal.unrecognized-tag.html"
      ],
      "settings": {
        "fontStyle": "",
        "foreground": "#88e6d6"
      }
    },
    {
      "name": "Entity Types",
      "scope": [
        "support.type",
        "meta.return.type",
        "entity.name.type",
        "meta.use.php"
      ],
      "settings": {
        "fontStyle": "normal",
        "foreground": "#88e6d6"
      }
    },
    {
      "name": "Entity Types",
      "scope": [
        "meta.type.tuple meta.brace"
      ],
      "settings": {
        "fontStyle": "normal"
      }
    },
    {
      "name": "Namespaces and Classes",
      "scope": [
        "entity.other.inherited-class",
        "support.orther.namespace.use",
        "support.other.namespace"
      ],
      "settings": {
        "fontStyle": "",
        "foreground": "#9ebecc"
      }
    },
    {
      "name": "Language methods",
      "scope": [
        "variable.language"
      ],
      "settings": {
        "foreground": "#a8f2ff"
      }
    },
    {
      "name": "Attributes, HTML Attributes",
      "scope": [
        "entity.other.attribute-name",
        "meta entity.other.attribute-name",
        "text.html.basic entity.other.attribute-name.html",
        "text.html.basic entity.other.attribute-name",
        "meta.directive.vue keyword.control"
      ],
      "settings": {
        "fontStyle": "normal",
        "foreground": "#cba0ff"
      }
    },
    {
      "name": "CSS Classes, IDs",
      "scope": [
        "entity.other.attribute-name.class",
        "entity.other.attribute-name.id",
        "entity.name.tag.css"
      ],
      "settings": {
        "fontStyle": "",
        "foreground": "#cba0ff"
      }
    },
    {
      "name": "Inserted",
      "scope": [
        "markup.inserted"
      ],
      "settings": {
        "foreground": "#97D484"
      }
    },
    {
      "name": "Deleted",
      "scope": [
        "markup.deleted"
      ],
      "settings": {
        "foreground": "#eb5757"
      }
    },
    {
      "name": "Changed",
      "scope": [
        "markup.changed"
      ],
      "settings": {
        "foreground": "#26B5CE"
      }
    },
    {
      "name": "URL",
      "scope": [
        "*url*",
        "*link*",
        "*uri*"
      ],
      "settings": {
        "fontStyle": "underline"
      }
    },
    {
      "name": "@include",
      "scope": [
        "keyword.control.at-rule"
      ],
      "settings": {
        "fontStyle": "normal",
        "foreground": "#1abdda"
      }
    },
    {
      "name": "&",
      "scope": [
        "entity.name.tag.reference"
      ],
      "settings": {
        "foreground": "#5fdfff"
      }
    },
    {
      "name": "Property names",
      "scope": [
        "support.type.property-name.json",
        "meta.objectliteral",
        "source.vue meta.object.member.ts meta.object.member.ts meta.object.member.ts",
        "source.css support.type.property-name",
        "source.sass support.type.property-name",
        "source.scss support.type.property-name",
        "source.less support.type.property-name",
        "source.stylus support.type.property-name",
        "source.postcss support.type.property-name",
        "entity.name.tag.yaml"
      ],
      "settings": {
        "fontStyle": "",
        "foreground": "#b1c5ca"
      }
    },
    {
      "name": "Attribute value unit",
      "scope": [
        "keyword.other.unit"
      ],
      "settings": {
        "foreground": "#59b13e"
      }
    },
    {
      "name": "Attribute value unit",
      "scope": [
        "source.env"
      ],
      "settings": {
        "foreground": "#ffd18b"
      }
    },
    {
      "name": "Attribute value unit",
      "scope": [
        "text.html.markdown",
        "string.other.link.title.markdown"
      ],
      "settings": {
        "foreground": "#e1e2e5"
      }
    },
    {
      "name": "Markdown Link",
      "scope": [
        "markup.underline.link.markdown"
      ],
      "settings": {
        "foreground": "#88e6d6"
      }
    },
    {
      "name": "Markdown Link",
      "scope": [
        "markup.fenced_code.block.markdown"
      ],
      "settings": {
        "foreground": "#ffd18b"
      }
    }
  ]
}